aat1/q5_sync_async_count_with_sync_async_rst/design/sync_sync_rst.v
module sync_sync_rst (
	input clk, rst,
	output reg [2:0] q
);

always @ (posedge clk) begin 

	if (rst) q <= 3'b0;
	else q <= q + 1;

end

endmodule

aat1/q5_sync_async_count_with_sync_async_rst/testbench/tb4.v
module tb;
reg clk, rst;
wire [2:0] q;

sync_sync_rst uut (clk, rst, q);

initial begin
    $dumpfile("waveform.vcd");
    $dumpvars(0, tb);
    rst = 1; clk = 1;
    #1 rst = 0;
    #99 $finish;
end

always #5 clk = ~clk;

endmodule

aat1/q5_sync_async_count_with_sync_async_rst/output/waveform.vcd
$date
	Sat Nov  2 10:43:57 2024
$end
$version
	Icarus Verilog
$end
$timescale
	1s
$end
$scope module tb $end
$var wire 3 ! q [2:0] $end
$var reg 1 " clk $end
$var reg 1 # rst $end
$scope module uut $end
$var wire 1 " clk $end
$var wire 1 # rst $end
$var reg 3 $ q [2:0] $end
$upscope $end
$upscope $end
$enddefinitions $end
$comment Show the parameter values. $end
$dumpall
$end
#0
$dumpvars
b0 $
1#
1"
b0 !
$end
#1
0#
#5
0"
#10
b1 !
b1 $
1"
#15
0"
#20
b10 !
b10 $
1"
#25
0"
#30
b11 !
b11 $
1"
#35
0"
#40
b100 !
b100 $
1"
#45
0"
#50
b101 !
b101 $
1"
#55
0"
#60
b110 !
b110 $
1"
#65
0"
#70
b111 !
b111 $
1"
#75
0"
#80
b0 !
b0 $
1"
#85
0"
#90
b1 !
b1 $
1"
#95
0"
#100
b10 !
b10 $
1"
