aat2/sync_FIFO/design/sync_fifo.v
module sync_fifo (clk, rst_n, wr_en, rd_en, wr_data, rd_data, full, empty);

input clk, rst_n, wr_en, rd_en;
input [7:0] wr_data;
output reg [7:0] rd_data;
output full, empty;

reg [4:0] wr_ptr, rd_ptr; // 5 bit write and read pointers (includes msb bits as needed to compare full/empty) 
reg [7:0] fifo_mem [15:0]; // define fifo memory with 16 words each of size 8 bits

always @ (posedge clk) begin
	if (!rst_n) begin
		wr_ptr <= 5'd0; rd_ptr <= 5'd0;
		rd_data <= 8'd0;
	end 

	if (wr_en & !full) begin
		fifo_mem[wr_ptr[4:0]] <= wr_data;
		wr_ptr <= wr_ptr + 4'd1;
	end

	if (rd_en & !empty) begin
		rd_data <= fifo_mem[rd_ptr[4:0]];
		rd_ptr <= rd_ptr + 4'd1;
	end
end

// checking if the ptr has rolled over (wrapped around) if yes then msb bits will be diff - then xor - high
assign full = (wr_ptr[4] ^ rd_ptr[4]) & (wr_ptr[3:0] == rd_ptr[3:0]);

assign empty = (wr_ptr == rd_ptr);

//assign empty = ~(wr_ptr[4] ^ rd_ptr[4]) & (wr_ptr[3:0] == rd_ptr[3:0]);

//using combinational as above doesnt give proper timing
//always @(posedge clk) begin
//    if (!rst_n) begin
//      full <= 1'b0;
//      empty <= 1'b1;
//    end else begin
//      full <= (wr_ptr[3] ^ rd_ptr[3]) && (wr_ptr[2:0] == rd_ptr[2:0]);
//      empty <= (wr_ptr == rd_ptr);
//    end
//  end

endmodule

aat2/sync_FIFO/testbench/tb.v
module tb;
reg clk, rst_n, wr_en, rd_en;
reg [7:0] wr_data;
wire full, empty;
wire [7:0] rd_data; 

integer i;

sync_fifo dut (clk, rst_n, wr_en, rd_en, wr_data, rd_data, full, empty);

initial begin
    $dumpfile("waveform.vcd");
    $dumpvars(0, tb);
end

  // Clock generation
  initial clk = 1;
  always #5 clk = ~clk; // 10ns clock period

  // Testbench logic
  initial begin
    // Initialize signals
    rst_n = 1'b1;
    wr_en = 1'b0;
    rd_en = 1'b0;
    wr_data = 8'b0;

    // Apply reset
    rst_n = 1'b0;
    #20 rst_n = 1'b1;

      // Write 16 data into the FIFO
      $display("Writing 16 data into FIFO...");
      repeat (16) begin
      	@(posedge clk);
        if (!full) begin
          wr_en = 1'b1;
          wr_data = wr_data + 1;
          #10;
        end
      end
      wr_en = 1'b0;

      // Wait for some time
      #30;

          // Test writing when FIFO is full
    $display("Testing write when FIFO is full...");
    wr_en = 1'b1;
    wr_data = 8'hFF; #10;
    if (full) $display("FIFO is full. Write ignored.");
    #10;
    wr_data = 8'd0;
    wr_en = 1'b0;
    #10;

      // Read 16 data from the FIFO
      $display("Reading 16 data from FIFO...");
      repeat (16) begin
      	@ (posedge clk);
        if (!empty) begin
          rd_en = 1'b1;
          #10;
        end
      end
      rd_en = 1'b0;

      // Wait for some time
      #50;  

    // Test reading when FIFO is empty
    $display("Testing read when FIFO is empty...");
    rd_en = 1'b1;
    if (empty) $display("FIFO is empty. Read ignored.");
    #10;
    rd_en = 1'b0;
    #10;

	// apply reset
	rst_n = 1'b0;
	#10 rst_n = 1'b1;
	
	// write new data to empty fifo and start reading
    wr_en = 1'b1;
    wr_data = 8'hFF; #10;
    wr_data = 8'hAB; #10;
    wr_data = 8'hEB; rd_en = 1'b1; #10;
    wr_data = 8'h66; #10;
	wr_data = 8'd0;
    wr_en = 1'b0;
    #20;
    rd_en = 1'b0;
    #10; 

   	rst_n = 1'b0;  

    // End simulation after extended time
    #100;
    $display("Testbench completed.");
    $finish;
  end

  // Monitor key signals
  initial begin
    $monitor("Time=%0t | wr_en=%b | rd_en=%b | wr_data=%h | rd_data=%h | full=%b | empty=%b",
             $time, wr_en, rd_en, wr_data, rd_data, full, empty);
  end

endmodule

aat2/sync_FIFO/output/waveform.vcd
$date
	Fri Dec 20 13:39:36 2024
$end
$version
	Icarus Verilog
$end
$timescale
	1s
$end
$scope module tb $end
$var wire 8 ! rd_data [7:0] $end
$var wire 1 " full $end
$var wire 1 # empty $end
$var reg 1 $ clk $end
$var reg 1 % rd_en $end
$var reg 1 & rst_n $end
$var reg 8 ' wr_data [7:0] $end
$var reg 1 ( wr_en $end
$scope module dut $end
$var wire 1 $ clk $end
$var wire 1 " full $end
$var wire 1 % rd_en $end
$var wire 1 & rst_n $end
$var wire 8 ) wr_data [7:0] $end
$var wire 1 ( wr_en $end
$var wire 1 # empty $end
$var reg 8 * rd_data [7:0] $end
$var reg 5 + rd_ptr [4:0] $end
$var reg 5 , wr_ptr [4:0] $end
$upscope $end
$upscope $end
$enddefinitions $end
$comment Show the parameter values. $end
$dumpall
$end
#0
$dumpvars
b0 ,
b0 +
b0 *
b0 )
0(
b0 '
0&
0%
1$
1#
0"
b0 !
$end
#5
0$
#10
1$
#15
0$
#20
0#
b1 ,
b1 '
b1 )
1(
1$
1&
#25
0$
#30
b10 ,
b10 '
b10 )
1$
#35
0$
#40
b11 ,
b11 '
b11 )
1$
#45
0$
#50
b100 ,
b100 '
b100 )
1$
#55
0$
#60
b101 ,
b101 '
b101 )
1$
#65
0$
#70
b110 ,
b110 '
b110 )
1$
#75
0$
#80
b111 ,
b111 '
b111 )
1$
#85
0$
#90
b1000 ,
b1000 '
b1000 )
1$
#95
0$
#100
b1001 ,
b1001 '
b1001 )
1$
#105
0$
#110
b1010 ,
b1010 '
b1010 )
1$
#115
0$
#120
b1011 ,
b1011 '
b1011 )
1$
#125
0$
#130
b1100 ,
b1100 '
b1100 )
1$
#135
0$
#140
b1101 ,
b1101 '
b1101 )
1$
#145
0$
#150
b1110 ,
b1110 '
b1110 )
1$
#155
0$
#160
b1111 ,
b1111 '
b1111 )
1$
#165
0$
#170
1"
b10000 ,
b10000 '
b10000 )
1$
#175
0$
#180
1$
0(
#185
0$
#190
1$
#195
0$
#200
1$
#205
0$
#210
1$
b11111111 '
b11111111 )
1(
#215
0$
#220
1$
#225
0$
#230
1$
0(
b0 '
b0 )
#235
0$
#240
0"
b1 +
b1 !
b1 *
1%
1$
#245
0$
#250
b10 +
b10 !
b10 *
1$
#255
0$
#260
b11 +
b11 !
b11 *
1$
#265
0$
#270
b100 +
b100 !
b100 *
1$
#275
0$
#280
b101 +
b101 !
b101 *
1$
#285
0$
#290
b110 +
b110 !
b110 *
1$
#295
0$
#300
b111 +
b111 !
b111 *
1$
#305
0$
#310
b1000 +
b1000 !
b1000 *
1$
#315
0$
#320
b1001 +
b1001 !
b1001 *
1$
#325
0$
#330
b1010 +
b1010 !
b1010 *
1$
#335
0$
#340
b1011 +
b1011 !
b1011 *
1$
#345
0$
#350
b1100 +
b1100 !
b1100 *
1$
#355
0$
#360
b1101 +
b1101 !
b1101 *
1$
#365
0$
#370
b1110 +
b1110 !
b1110 *
1$
#375
0$
#380
b1111 +
b1111 !
b1111 *
1$
#385
0$
#390
0"
1#
b10000 +
b10000 !
b10000 *
1$
#395
0$
#400
1$
0%
#405
0$
#410
1$
#415
0$
#420
1$
#425
0$
#430
1$
#435
0$
#440
1$
#445
0$
#450
1$
1%
#455
0$
#460
1$
0%
#465
0$
#470
b0 !
b0 *
b0 +
1#
b0 ,
1$
0&
#475
0$
#480
0#
b1 ,
1$
b11111111 '
b11111111 )
1(
1&
#485
0$
#490
b10 ,
1$
b10101011 '
b10101011 )
#495
0$
#500
b1 +
b11111111 !
b11111111 *
b11 ,
1$
1%
b11101011 '
b11101011 )
#505
0$
#510
b10 +
b10101011 !
b10101011 *
b100 ,
1$
b1100110 '
b1100110 )
#515
0$
#520
b11 +
b11101011 !
b11101011 *
1$
0(
b0 '
b0 )
#525
0$
#530
1#
b100 +
b1100110 !
b1100110 *
1$
#535
0$
#540
1$
0%
#545
0$
#550
b0 !
b0 *
b0 +
1#
b0 ,
1$
0&
