aat2/seq_det/design/seq_det.v
module seq_det (input clk, rst_n, in, output reg out);

parameter [1:0] A=2'b00, B=2'b01, C=2'b10, D=2'b11;
reg [1:0] PS, NS;

always @ (posedge clk, negedge rst_n) begin
	if (!rst_n) begin PS <= A;
	out <= 1'b0; end
	else PS <= NS;
end

always @ (*) begin 
	NS = A;
	out = 1'b0;

	case(PS)
	A: if (in) begin NS = B; out = 1'b0; end else begin NS = A; out = 1'b0; end// reset
	B: if (in) begin NS = D; out = 1'b0; end else begin NS = C; out = 1'b0; end  // '1' detected
	C: if (in) begin NS = B; out = 1'b1; end else begin NS = A; out = 1'b0; end // '10' detected
	D: if (in) begin NS = D; out = 1'b0; end else begin NS = A; out = 1'b1; end  // '11' detected
	default: begin NS = A; out = 1'b0; end
	endcase
end

endmodule

aat2/seq_det/testbench/tb.v
module tb;
    reg clk, rst_n, in;
    wire out;

    seq_det uut (clk, rst_n, in, out);
    
    // Initial setup
    initial begin
        $dumpfile("waveform.vcd");
        $dumpvars(0, tb);
        clk = 1'b0;  // Start with clock low
        rst_n = 1'b0;  // Apply reset
        in = 1'b0;
        #3 rst_n = 1'b1;  // Deassert reset after 3 time units 
    end


    // Correct clock toggling
    always #5 clk = ~clk;

    // Input stimulus
    initial begin
        @(posedge clk); in = 1'b0; // Idle state
        @(posedge clk); in = 1'b1;  // Start sequence
        @(posedge clk); in = 1'b0;  // '10'
        @(posedge clk); in = 1'b1;  // '101' detected
        @(posedge clk); in = 1'b1;  // Overlapping '110' detected
        @(posedge clk); in = 1'b0;  // Resetting to '10'
        @(posedge clk); in = 1'b1;  // Another '101'
        @(posedge clk); in = 1'b0;  // Start of '101' again
        @(posedge clk); in = 1'b1;  // Overlapping '101' detected
        @(posedge clk); in = 1'b0; 
        $finish;     // End simulation
    end

    // for (i = 0; i < 20; i = i + 1) begin
    //     @ (posedge clk);
    //     in = $random;    
    // end

     // Monitor signals
    initial begin
        $monitor("Time: %0t | clk: %b | rst: %b | in: %b | out: %b", $time, clk, rst_n, in, out);
    end

    // Monitor outputs every 10 time units
    //initial begin
    //    forever begin
    //        #10;
    //        $display("Time=%0t | clk=%b | rst=%b | x=%b | z=%b | PS=%b", 
    //                 $time, clk, rst, x, z, uut.PS);
    //    end
    //end


endmodule

aat2/seq_det/output/waveform.vcd
$date
	Sat Jan  4 21:07:24 2025
$end
$version
	Icarus Verilog
$end
$timescale
	1s
$end
$scope module tb $end
$var wire 1 ! out $end
$var reg 1 " clk $end
$var reg 1 # in $end
$var reg 1 $ rst_n $end
$scope module uut $end
$var wire 1 " clk $end
$var wire 1 # in $end
$var wire 1 $ rst_n $end
$var parameter 2 % A $end
$var parameter 2 & B $end
$var parameter 2 ' C $end
$var parameter 2 ( D $end
$var reg 2 ) NS [1:0] $end
$var reg 2 * PS [1:0] $end
$var reg 1 ! out $end
$upscope $end
$upscope $end
$enddefinitions $end
$comment Show the parameter values. $end
$dumpall
b11 (
b10 '
b1 &
b0 %
$end
#0
$dumpvars
b0 *
b0 )
0$
0#
0"
0!
$end
#3
1$
#5
1"
#10
0"
#15
b1 )
1#
1"
#20
0"
#25
b1 *
b10 )
0#
1"
#30
0"
#35
1!
b10 *
b1 )
1#
1"
#40
0"
#45
0!
b11 )
b1 *
1"
#50
0"
#55
1!
b11 *
b0 )
0#
1"
#60
0"
#65
b0 *
b1 )
0!
1#
1"
#70
0"
#75
b1 *
b10 )
0#
1"
#80
0"
#85
1!
b10 *
b1 )
1#
1"
#90
0"
#95
b1 *
0!
b10 )
0#
1"
