aat1/q3_jkff_async_high_reset_sync_low_set/design/jkff.v
module jkff (
	input j, k, clk, rst, setlow,
	output reg q
);

always @ (posedge clk or posedge rst) begin

	if (rst) q <= 1'b0; // async active high reset
	else if (!setlow) q <= 1'b1; // sync active low set
	else begin
		case({j,k})
			2'b00: q <= q;    // Hold
			2'b01: q <= 1'b0; // Reset
			2'b10: q <= 1'b1; // Set
			2'b11: q <= ~q;   // Toggle
			default: q <= q;
		endcase
	end
end

endmodule

aat1/q3_jkff_async_high_reset_sync_low_set/testbench/tb.v
module tb;
reg j, k, clk, rst, setlow;
wire q;

jkff uut (j, k, clk, rst, setlow, q);

initial begin
	$dumpfile("waveform.vcd");
	$dumpvars(0, tb);

	rst=1'b1;
	setlow=1'b1;
	#1 rst=1'b0;
	#6 setlow=1'b0;
	#4 setlow=1'b1;
	#10 rst=1'b1;
	#1 rst=1'b0;

end

always #5 clk = ~clk;

initial begin 
  clk=1'b1;
  j=1'b0; k=1'b0; #10;
  j=1'b0; k=1'b1; #10;
  j=1'b1; k=1'b0; #10;
  j=1'b1; k=1'b1; #10;
  $finish;
end

endmodule

aat1/q3_jkff_async_high_reset_sync_low_set/output/waveform.vcd
$date
	Wed Oct 30 19:34:48 2024
$end
$version
	Icarus Verilog
$end
$timescale
	1s
$end
$scope module tb $end
$var wire 1 ! q $end
$var reg 1 " clk $end
$var reg 1 # j $end
$var reg 1 $ k $end
$var reg 1 % rst $end
$var reg 1 & setlow $end
$scope module uut $end
$var wire 1 " clk $end
$var wire 1 # j $end
$var wire 1 $ k $end
$var wire 1 % rst $end
$var wire 1 & setlow $end
$var reg 1 ! q $end
$upscope $end
$upscope $end
$enddefinitions $end
$comment Show the parameter values. $end
$dumpall
$end
#0
$dumpvars
1&
1%
0$
0#
1"
0!
$end
#1
0%
#5
0"
#7
0&
#10
1!
1"
1$
#11
1&
#15
0"
#20
1"
0$
1#
#21
0!
1%
#22
0%
#25
0"
#30
1!
1"
1$
#35
0"
#40
0!
1"
